dopyqo/__init__.py
dopyqo/calc_matrix_elements.py
dopyqo/calc_pseudo_pot.py
dopyqo/colors.py
dopyqo/cube.py
dopyqo/eri_pair_densities.py
dopyqo/fci_vector_matrix.py
dopyqo/hamiltonian.py
dopyqo/info.py
dopyqo/plotting.py
dopyqo/pseudopot.py
dopyqo/transform_matrices.py
dopyqo/units.py
dopyqo/wannier90.py
dopyqo/wfc.py
dopyqo/wfc_spin.py
dopyqo/xsf.py
dopyqo/helpers/atoms.py
dopyqo/helpers/config.py
dopyqo/helpers/matrix_elements.py
dopyqo/helpers/printing.py
dopyqo/helpers/tcc_helpers.py
dopyqo/helpers/vqe_helpers.py
dopyqo/scripts/banners.py
dopyqo/scripts/main.py
dopyqo-0.1.0.dist-info/licenses/LICENSE.txt
dopyqo-0.1.0.dist-info/METADATA
dopyqo-0.1.0.dist-info/WHEEL
dopyqo-0.1.0.dist-info/entry_points.txt
dopyqo-0.1.0.dist-info/top_level.txt
dopyqo-0.1.0.dist-info/RECORD
