Metadata-Version: 2.4
Name: dopyqo
Version: 0.1.0
Summary: Dopyqo: a many-body post-processing tool for Quantum ESPRESSO
Author: Alexander Rehn, Erik Hansen, Jasper Nickelsen
Author-email: Erik Schultheis <Erik.Schultheis@dlr.de>, Gabriel Breuil <Gabriel.Breuil@dlr.de>
License: The GNU General Public License (GPL-2.0)
Project-URL: Repository, https://github.com/dlr-wf/Dopyqo
Project-URL: Issues, https://github.com/dlr-wf/Dopyqo/issues
Keywords: dopyqo,Quantum ESPRESSO,many-body,Bader charges,FCI,quantum computing,VQE
Classifier: Intended Audience :: Science/Research
Classifier: Programming Language :: Python :: 3
Classifier: Programming Language :: Python :: 3.8
Classifier: Programming Language :: Python :: 3.9
Classifier: Programming Language :: Python :: 3.10
Classifier: Programming Language :: Python :: 3.11
Requires-Python: >=3.10
License-File: LICENSE.txt
Requires-Dist: numpy==1.26.4
Requires-Dist: h5py==3.13.0
Requires-Dist: xmltodict==0.13.0
Requires-Dist: qiskit==1.4.0
Requires-Dist: qiskit-nature==0.7.2
Requires-Dist: qiskit-algorithms==0.3.1
Requires-Dist: pyscf==2.8.0
Requires-Dist: matplotlib==3.10.1
Requires-Dist: termplotlib==0.3.9
Requires-Dist: scipy==1.15.2
Requires-Dist: numba==0.60.0
Requires-Dist: tencirchem-ng==2024.10
Requires-Dist: excitationsolve
Requires-Dist: pyvista[jupyter]==0.45.3
Provides-Extra: rs
Requires-Dist: dopyqo-rs; extra == "rs"
Provides-Extra: gpu
Requires-Dist: cupy; extra == "gpu"
Provides-Extra: all
Requires-Dist: dopyqo-rs; extra == "all"
Requires-Dist: cupy; extra == "all"
Dynamic: license-file
